kilojoule/__init__.py
kilojoule/_version.py
kilojoule/chemical.py
kilojoule/common.py
kilojoule/constants.py
kilojoule/display.py
kilojoule/export.py
kilojoule/humidair.py
kilojoule/idealgas.py
kilojoule/magics.py
kilojoule/organization.py
kilojoule/plotting.py
kilojoule/realfluid.py
kilojoule/solution_hash.py
kilojoule/solve.py
kilojoule/transport.py
kilojoule/units.py
kilojoule/fluids/__init__.py
kilojoule/properties/__init__.py
kilojoule/properties/idealgas.py
kilojoule/properties/realfluid.py
kilojoule/schemdraw/__init__.py
kilojoule/schemdraw/thermo/__init__.py
kilojoule/schemdraw/thermo/common.py
kilojoule/schemdraw/thermo/compressor.py
kilojoule/schemdraw/thermo/hx.py
kilojoule/schemdraw/thermo/pipe.py
kilojoule/schemdraw/thermo/piston.py
kilojoule/schemdraw/thermo/pump.py
kilojoule/schemdraw/thermo/shaft.py
kilojoule/schemdraw/thermo/turbine.py
kilojoule/schemdraw/thermo/valve.py
kilojoule/tables/Bergman.py
kilojoule/tables/Cengel.py
kilojoule/tables/__init__.py
kilojoule/tables/air.py
kilojoule/tables/water.py
kilojoule/templates/SI.py
kilojoule/templates/SI_C.py
kilojoule/templates/USCS_F.py
kilojoule/templates/USCS_R.py
kilojoule/templates/__init__.py
kilojoule/templates/colab.py
kilojoule/templates/default.py
kilojoule/templates/fluids.py
kilojoule/templates/ht.py
kilojoule/templates/humidair_USCS_F.py
kilojoule/templates/humidair_default.py
kilojoule/templates/kSI.py
kilojoule/templates/kSI_C.py
kilojoule/templates/kSI_K.py
kilojoule/templates/thermo.py
kilojoule/thermo/__init__.py
kilojoule-0.4.1.dist-info/licenses/AUTHORS.rst
kilojoule-0.4.1.dist-info/licenses/LICENSE.txt
kilojoule-0.4.1.dist-info/METADATA
kilojoule-0.4.1.dist-info/WHEEL
kilojoule-0.4.1.dist-info/top_level.txt
kilojoule-0.4.1.dist-info/RECORD
