Metadata-Version: 2.4
Name: kilojoule
Version: 0.4.1
Summary: A convenience package for engineering calculations with a focus on fluids mechanics, thermodynamics, and heat transfer
Home-page: https://github.com/johnfmaddox/kilojoule
Author: Jack Maddox
Author-email: jackmaddox@gmail.com
Classifier: Programming Language :: Python :: 3
Classifier: License :: OSI Approved :: MIT License
Classifier: Operating System :: OS Independent
Requires-Python: >=3.8
License-File: LICENSE.txt
License-File: AUTHORS.rst
Requires-Dist: numpy
Requires-Dist: scipy
Requires-Dist: sympy
Requires-Dist: pandas
Requires-Dist: matplotlib
Requires-Dist: pint
Requires-Dist: pint-pandas
Requires-Dist: uncertainties
Requires-Dist: coolprop
Requires-Dist: pyromat
Requires-Dist: regex
Requires-Dist: rich
Requires-Dist: schemdraw
Requires-Dist: sigfig
Requires-Dist: emoji
Requires-Dist: icecream
Requires-Dist: seaborn
Dynamic: author
Dynamic: author-email
Dynamic: classifier
Dynamic: description
Dynamic: description-content-type
Dynamic: home-page
Dynamic: license-file
Dynamic: requires-dist
Dynamic: requires-python
Dynamic: summary
